odoo9_addon_auth_session_timeout-9.0.1.0.0.99.dev11-py2.7-nspkg.pth
odoo9_addon_auth_session_timeout-9.0.1.0.0.99.dev11.dist-info/DESCRIPTION.rst
odoo9_addon_auth_session_timeout-9.0.1.0.0.99.dev11.dist-info/METADATA
odoo9_addon_auth_session_timeout-9.0.1.0.0.99.dev11.dist-info/RECORD
odoo9_addon_auth_session_timeout-9.0.1.0.0.99.dev11.dist-info/WHEEL
odoo9_addon_auth_session_timeout-9.0.1.0.0.99.dev11.dist-info/metadata.json
odoo9_addon_auth_session_timeout-9.0.1.0.0.99.dev11.dist-info/namespace_packages.txt
odoo9_addon_auth_session_timeout-9.0.1.0.0.99.dev11.dist-info/top_level.txt
odoo_addons/auth_session_timeout/README.rst
odoo_addons/auth_session_timeout/__init__.py
odoo_addons/auth_session_timeout/__openerp__.py
odoo_addons/auth_session_timeout/data/ir_config_parameter_data.xml
odoo_addons/auth_session_timeout/i18n/ar.po
odoo_addons/auth_session_timeout/i18n/auth_session_timeout.pot
odoo_addons/auth_session_timeout/i18n/ca.po
odoo_addons/auth_session_timeout/i18n/da.po
odoo_addons/auth_session_timeout/i18n/de.po
odoo_addons/auth_session_timeout/i18n/el_GR.po
odoo_addons/auth_session_timeout/i18n/es.po
odoo_addons/auth_session_timeout/i18n/es_ES.po
odoo_addons/auth_session_timeout/i18n/fi.po
odoo_addons/auth_session_timeout/i18n/fr.po
odoo_addons/auth_session_timeout/i18n/fr_CH.po
odoo_addons/auth_session_timeout/i18n/hr.po
odoo_addons/auth_session_timeout/i18n/hr_HR.po
odoo_addons/auth_session_timeout/i18n/it.po
odoo_addons/auth_session_timeout/i18n/nl.po
odoo_addons/auth_session_timeout/i18n/pt_BR.po
odoo_addons/auth_session_timeout/i18n/sl.po
odoo_addons/auth_session_timeout/i18n/tr.po
odoo_addons/auth_session_timeout/i18n/tr_TR.po
odoo_addons/auth_session_timeout/i18n/zh_CN.po
odoo_addons/auth_session_timeout/models/__init__.py
odoo_addons/auth_session_timeout/models/ir_config_parameter.py
odoo_addons/auth_session_timeout/models/res_users.py
odoo_addons/auth_session_timeout/static/description/icon.png
odoo_addons/auth_session_timeout/tests/__init__.py
odoo_addons/auth_session_timeout/tests/test_ir_config_parameter.py
odoo_addons/auth_session_timeout/tests/test_res_user.py
